gguf_code/__init__.py
gguf_code/__main__.py
gguf_code-0.0.1.dist-info/LICENSE
gguf_code-0.0.1.dist-info/WHEEL
gguf_code-0.0.1.dist-info/METADATA
gguf_code-0.0.1.dist-info/RECORD
