Metadata-Version: 2.1
Name: gguf-code
Version: 0.0.1
Summary: GGUF code
Author-email: gguf <info@gguf.us>
Classifier: License :: OSI Approved :: MIT License
Project-URL: Issues, https://github.com/calcuis/gguf-coder/issues
Project-URL: Repository, https://github.com/calcuis/gguf-coder
